fun_text_joe/__init__.py
fun_text_joe_demo-0.0.3.dist-info/METADATA
fun_text_joe_demo-0.0.3.dist-info/WHEEL
fun_text_joe_demo-0.0.3.dist-info/licenses/LICENSE
fun_text_joe_demo-0.0.3.dist-info/RECORD
