Metadata-Version: 2.4
Name: fun-text-joe-demo
Version: 0.0.3
Summary: A small example package creating fun text greetings
Author-email: Joe <joe@example.com>
License-File: LICENSE
Classifier: License :: OSI Approved :: MIT License
Classifier: Operating System :: OS Independent
Classifier: Programming Language :: Python :: 3
Requires-Python: >=3.7
